{
    "videoService": "សេវាកម្មថតវីដេអូ",
    "photoService" : "សេវាកម្មថតរូប",
    "socialMediaMarketing":"ទីផ្សារប្រព័ន្ធផ្សព្វផ្សាយសង្គម",
    "webDevelopment":"ការអភិវឌ្ឍន៍គេហទំព័រ",
    "Event":"ព្រឹត្តិការណ៍",
    "Commercial" : "ពាណិជ្ជកម្ម",
    "Documentary" : "ឯកសារ",
    "Live Strem" : "ផ្សាយ​ផ្ទាល់",
    "Sort Film" : "ខ្សែ​ភាពយន្ត​ខ្លី",
    "Travel" : "ការធ្វើដំណើរ",
    "Studio" : "ស្ទូឌីយោ",
    "Product" : "ផលិតផល",
    "youtube" : "យូធូប",
    "contact" : "ទំនាក់ទំនង",
    "aboutus" : "អំពី​ពួក​យើង",
    "copyright" : "ចម្លងសិទ្ធិ ",
    "more" : "មើល​ច្រើន​ទៀត",
    "video" : "វីដេអូ",
    "team" : "ក្រុមការងារ",
    "company": "ព័ត៌មានក្រុមហ៊ុន",
    "openingHour" : "ម៉ោងបើកក្រុមហ៊ុន",
    "ourPartners" : "ដៃគូសហការរបស់យើង",
    "viewTeam" : "មើលក្រុម",
    "yourName" : "ឈ្មោះ​របស់​អ្នក",
    "email" : "អ៊ីមែល",
    "subject" : "ប្រធានបទ",
    "message" : "សាររបស់អ្នក",
    "enter" : "បញ្ចូល",
    "send" : "ផ្ញើ",
    "sending" : "កំពុងផ្ញើ",
    "YourNameRequired" : "វាលឈ្មោះរបស់អ្នកត្រូវបានទាមទារ។",
    "emailRequired" : "វាលអ៊ីមែលត្រូវបានទាមទារ។",
    "subjectRequired" : "ប្រធានបទត្រូវបានទាមទារ។",
    "messageRequired" : "សារត្រូវបានទាមទារ។",
    "captchaRequired" : "reCAPTCHA ការផ្ទៀងផ្ទាត់ត្រូវបានទាមទារ។",
    "getInTouch" : "ទាក់ទង",
    "facebook" : "ហ្វេសប៊ុក"
  }
